quark_plugin_ibm/__init__.py
quark_plugin_ibm/circuit_to_estimator.py
quark_plugin_ibm/circuit_to_sampler.py
quark_plugin_ibm-0.2.0.dist-info/licenses/LICENSE
quark_plugin_ibm-0.2.0.dist-info/licenses/NOTICE
quark_plugin_ibm-0.2.0.dist-info/METADATA
quark_plugin_ibm-0.2.0.dist-info/WHEEL
quark_plugin_ibm-0.2.0.dist-info/top_level.txt
quark_plugin_ibm-0.2.0.dist-info/RECORD
