Metadata-Version: 2.4
Name: QUARK-plugin-ibm
Version: 0.2.0
License-Expression: Apache-2.0
Project-URL: Homepage, https://github.com/QUARK-framework/QUARK-plugin-ibm
Classifier: Programming Language :: Python :: 3
Classifier: Operating System :: OS Independent
Requires-Python: >=3.12
License-File: LICENSE
License-File: NOTICE
Requires-Dist: quark-framework>=0.4.5
Requires-Dist: qiskit>=2.2.1
Dynamic: license-file
